{"_type":"export","__export_format":4,"__export_date":"2021-11-12T13:32:30.134Z","__export_source":"insomnia.desktop.app:v2021.6.0","resources":[{"_id":"req_f5ceb2ccdec043f5a645aa09ce11a75d","parentId":"fld_f76ab0bd6f5f4616ab9b568c6d02c187","modified":1636723465508,"created":1636722865887,"url":"https://dkanvas.herokuapp.com/api/submissions/","name":"Listar submissões","description":"","method":"GET","body":{},"parameters":[],"headers":[{"id":"pair_fe02f11f957946458a561e2d21cbd0f4","name":"Authorization","value":"token 2acedeac00f7260545f761fc444d366dece8dc03","description":""}],"authentication":{},"metaSortKey":-1636722865887,"isPrivate":false,"settingStoreCookies":true,"settingSendCookies":true,"settingDisableRenderRequestBody":false,"settingEncodeUrl":true,"settingRebuildPath":true,"settingFollowRedirects":"global","_type":"request"},{"_id":"fld_f76ab0bd6f5f4616ab9b568c6d02c187","parentId":"wrk_6b6bbda01c4f48afb01b2b6240a4e5eb","modified":1636721388968,"created":1636721388968,"name":"atividades e submissões","description":"","environment":{},"environmentPropertyOrder":null,"metaSortKey":-1636721388968,"_type":"request_group"},{"_id":"wrk_6b6bbda01c4f48afb01b2b6240a4e5eb","parentId":null,"modified":1625581781989,"created":1625581781989,"name":"Insomnia","description":"","scope":"design","_type":"workspace"},{"_id":"req_65c9982ac3114261aa27607f8d1c24db","parentId":"fld_f76ab0bd6f5f4616ab9b568c6d02c187","modified":1636723495179,"created":1636722615188,"url":"https://dkanvas.herokuapp.com/api/submissions/1/","name":"editar nota","description":"","method":"PUT","body":{"mimeType":"application/json","text":"{\n    \"grade\": 10\n}\n"},"parameters":[],"headers":[{"id":"pair_91b6766b03864347b9ac1cfff80eb0d4","name":"Authorization","value":"token a24e2f725b9d78e333b281652550350920dc1774","description":""},{"name":"Content-Type","value":"application/json","id":"pair_4a80ec9a7e464984801ebed07967aef6"}],"authentication":{},"metaSortKey":-1636722615188,"isPrivate":false,"settingStoreCookies":true,"settingSendCookies":true,"settingDisableRenderRequestBody":false,"settingEncodeUrl":true,"settingRebuildPath":true,"settingFollowRedirects":"global","_type":"request"},{"_id":"req_ced74f435ae74f938a23defecbb3205b","parentId":"fld_f76ab0bd6f5f4616ab9b568c6d02c187","modified":1636723302755,"created":1636722423406,"url":"https://dkanvas.herokuapp.com/api/activities/1/submissions/","name":"submeter","description":"","method":"POST","body":{"mimeType":"application/json","text":"{\n    \"repo\": \"http://gitlab.com/kenzie_pet\"\n}\n"},"parameters":[],"headers":[{"name":"Content-Type","value":"application/json","id":"pair_f30eca949d034567bd3ae590d29b6a65"},{"id":"pair_b7e5c501f9de4b679a70c3553453dd17","name":"Authorization","value":"token 2acedeac00f7260545f761fc444d366dece8dc03","description":""}],"authentication":{},"metaSortKey":-1636722423406,"isPrivate":false,"settingStoreCookies":true,"settingSendCookies":true,"settingDisableRenderRequestBody":false,"settingEncodeUrl":true,"settingRebuildPath":true,"settingFollowRedirects":"global","_type":"request"},{"_id":"req_f4959de1ffbf47ff931351d94281f020","parentId":"fld_f76ab0bd6f5f4616ab9b568c6d02c187","modified":1636723306055,"created":1636722258586,"url":"https://dkanvas.herokuapp.com/api/activities/2/","name":"Editar","description":"","method":"PUT","body":{"mimeType":"application/json","text":"{\n    \"title\": \"Kenzie DOGS\",\n    \"points\": 30\n}\n"},"parameters":[],"headers":[{"name":"Content-Type","value":"application/json","id":"pair_c6c145109d0e43f7b43f6e9e45ec39f5"},{"id":"pair_1b0ab1de402d4ac6bcfd6b335ee27277","name":"Authorization","value":"token 9ffe4b3a3d9e9ed4ba24573ec35be7e0fc3bd9e3","description":""}],"authentication":{},"metaSortKey":-1636722258586,"isPrivate":false,"settingStoreCookies":true,"settingSendCookies":true,"settingDisableRenderRequestBody":false,"settingEncodeUrl":true,"settingRebuildPath":true,"settingFollowRedirects":"global","_type":"request"},{"_id":"req_6a82929c238e4914a5d728e1d42d8739","parentId":"fld_f76ab0bd6f5f4616ab9b568c6d02c187","modified":1636723415478,"created":1636722034478,"url":"https://dkanvas.herokuapp.com/api/activities/","name":"listar atividades e submissões","description":"","method":"GET","body":{},"parameters":[],"headers":[{"id":"pair_f101a7a175724b3ca7aac99df8f63755","name":"Authorization","value":"token 2acedeac00f7260545f761fc444d366dece8dc03","description":""}],"authentication":{},"metaSortKey":-1636722034478,"isPrivate":false,"settingStoreCookies":true,"settingSendCookies":true,"settingDisableRenderRequestBody":false,"settingEncodeUrl":true,"settingRebuildPath":true,"settingFollowRedirects":"global","_type":"request"},{"_id":"req_6248c02298424312a854ea83f769b733","parentId":"fld_f76ab0bd6f5f4616ab9b568c6d02c187","modified":1636722365620,"created":1636721496073,"url":"https://dkanvas.herokuapp.com/api/activities/","name":"Criar atividade","description":"","method":"POST","body":{"mimeType":"application/json","text":"{\n    \"title\": \"Kenzie Pet 2\",\n    \"points\": 10\n}\n"},"parameters":[],"headers":[{"name":"Content-Type","value":"application/json","id":"pair_b18154d7f0fe45478e2ef2aa6636de3d"},{"id":"pair_480c3df5aaf64b03af6323911f97bf1b","name":"Authorization","value":"token 9ffe4b3a3d9e9ed4ba24573ec35be7e0fc3bd9e3","description":""}],"authentication":{},"metaSortKey":-1636721496073,"isPrivate":false,"settingStoreCookies":true,"settingSendCookies":true,"settingDisableRenderRequestBody":false,"settingEncodeUrl":true,"settingRebuildPath":true,"settingFollowRedirects":"global","_type":"request"},{"_id":"req_f1f0a755bebd4efea191d1e8f2e449ed","parentId":"fld_56bcb7db823b459e92a0cdeae1060ea6","modified":1636723333897,"created":1636329033196,"url":"https://dkanvas.herokuapp.com/api/login/","name":"Login","description":"","method":"POST","body":{"mimeType":"application/json","text":"{\n    \"username\": \"Student\",\n    \"password\": \"1234\"\n}\n\n"},"parameters":[],"headers":[{"name":"Content-Type","value":"application/json","id":"pair_b9fc87fe663244118d178e72687a97f1"},{"id":"pair_080e7d47ff364b5781f460353c2db948","name":"","value":"","description":""}],"authentication":{},"metaSortKey":-1636329033196,"isPrivate":false,"settingStoreCookies":true,"settingSendCookies":true,"settingDisableRenderRequestBody":false,"settingEncodeUrl":true,"settingRebuildPath":true,"settingFollowRedirects":"global","_type":"request"},{"_id":"fld_56bcb7db823b459e92a0cdeae1060ea6","parentId":"wrk_6b6bbda01c4f48afb01b2b6240a4e5eb","modified":1636328770001,"created":1636328739193,"name":"User","description":"","environment":{},"environmentPropertyOrder":null,"metaSortKey":-1636328749805,"_type":"request_group"},{"_id":"req_829055197bec41de9a5560175a3e4d77","parentId":"fld_56bcb7db823b459e92a0cdeae1060ea6","modified":1636723098952,"created":1636328811094,"url":"https://dkanvas.herokuapp.com/api/accounts/","name":"Cadastrar","description":"","method":"POST","body":{"mimeType":"application/json","text":"{\n    \"username\": \"Instructor15\",\n    \"password\": \"1234\",\n    \"is_superuser\": true, \n    \"is_staff\": true \n}\n"},"parameters":[],"headers":[{"name":"Content-Type","value":"application/json","id":"pair_8993404915f4448da0bd10d3129e56b8"}],"authentication":{},"metaSortKey":-1636328811095,"isPrivate":false,"settingStoreCookies":true,"settingSendCookies":true,"settingDisableRenderRequestBody":false,"settingEncodeUrl":true,"settingRebuildPath":true,"settingFollowRedirects":"global","_type":"request"},{"_id":"req_8aaf69132fae45e182744c45d650462b","parentId":"fld_0f528f76dd0e4da881432a393d3bd05b","modified":1636721687854,"created":1636629232606,"url":"https://dkanvas.herokuapp.com/api/courses/4/registrations/","name":"vincular alunos ao curso","description":"","method":"PUT","body":{"mimeType":"application/json","text":"{\n    \"user_ids\": [22, 23]\n}\n"},"parameters":[],"headers":[{"name":"Content-Type","value":"application/json","id":"pair_7d9e2bcc92514bd1adb8508dd37d3157"},{"id":"pair_b048fb073b264938935a6b5d6d12452c","name":"Authorization","value":"token 9ffe4b3a3d9e9ed4ba24573ec35be7e0fc3bd9e3","description":""}],"authentication":{},"metaSortKey":-1636629232606,"isPrivate":false,"settingStoreCookies":true,"settingSendCookies":true,"settingDisableRenderRequestBody":false,"settingEncodeUrl":true,"settingRebuildPath":true,"settingFollowRedirects":"global","_type":"request"},{"_id":"fld_0f528f76dd0e4da881432a393d3bd05b","parentId":"wrk_6b6bbda01c4f48afb01b2b6240a4e5eb","modified":1636328749755,"created":1636328749755,"name":"Curso","description":"","environment":{},"environmentPropertyOrder":null,"metaSortKey":-1636328749755,"_type":"request_group"},{"_id":"req_8175a9749cb4490da452dcae6d91e256","parentId":"fld_0f528f76dd0e4da881432a393d3bd05b","modified":1636720994790,"created":1636629165863,"url":"https://dkanvas.herokuapp.com/api/courses/1","name":"curso e alunos por ID","description":"","method":"GET","body":{},"parameters":[],"headers":[],"authentication":{},"metaSortKey":-1636629165863,"isPrivate":false,"settingStoreCookies":true,"settingSendCookies":true,"settingDisableRenderRequestBody":false,"settingEncodeUrl":true,"settingRebuildPath":true,"settingFollowRedirects":"global","_type":"request"},{"_id":"req_5bb42724e6db4613b89f01c2ef13249a","parentId":"fld_0f528f76dd0e4da881432a393d3bd05b","modified":1636721052435,"created":1636628877398,"url":"https://dkanvas.herokuapp.com/api/courses/1/","name":"Excluir","description":"","method":"DELETE","body":{},"parameters":[],"headers":[{"id":"pair_7911caa9a6ce4a9587754a4a1f79d2d0","name":"Authorization","value":"token 9ffe4b3a3d9e9ed4ba24573ec35be7e0fc3bd9e3","description":""}],"authentication":{},"metaSortKey":-1636628877398,"isPrivate":false,"settingStoreCookies":true,"settingSendCookies":true,"settingDisableRenderRequestBody":false,"settingEncodeUrl":true,"settingRebuildPath":true,"settingFollowRedirects":"global","_type":"request"},{"_id":"req_8f463bebbe4d4166a62e21b3036ce32b","parentId":"fld_0f528f76dd0e4da881432a393d3bd05b","modified":1636721020720,"created":1636628720996,"url":"https://dkanvas.herokuapp.com/api/courses/1/","name":"Editar","description":"","method":"PUT","body":{"mimeType":"application/json","text":"{\n    \"name\": \"Python Django\"\n}\n"},"parameters":[],"headers":[{"name":"Content-Type","value":"application/json","id":"pair_bbf585b34fa94ea9a1d3ef52c2b1d7e4"},{"id":"pair_e73e058c816e4dca928e80f9466eef66","name":"Authorization","value":"token 9ffe4b3a3d9e9ed4ba24573ec35be7e0fc3bd9e3","description":""}],"authentication":{},"metaSortKey":-1636628720996,"isPrivate":false,"settingStoreCookies":true,"settingSendCookies":true,"settingDisableRenderRequestBody":false,"settingEncodeUrl":true,"settingRebuildPath":true,"settingFollowRedirects":"global","_type":"request"},{"_id":"req_25fde4e0bd0b4c529d722f85c93267c8","parentId":"fld_0f528f76dd0e4da881432a393d3bd05b","modified":1636629088748,"created":1636628562471,"url":"https://dkanvas.herokuapp.com/api/courses/","name":"LIstar Cursos e alunos","description":"","method":"GET","body":{"mimeType":"application/json","text":""},"parameters":[],"headers":[{"name":"Content-Type","value":"application/json","id":"pair_696123cb4f1e42f6b72c758ebcfd1f2a"}],"authentication":{},"metaSortKey":-1636628562471,"isPrivate":false,"settingStoreCookies":true,"settingSendCookies":true,"settingDisableRenderRequestBody":false,"settingEncodeUrl":true,"settingRebuildPath":true,"settingFollowRedirects":"global","_type":"request"},{"_id":"req_4a1b2f4579dd4d49905736bc70ee6346","parentId":"fld_0f528f76dd0e4da881432a393d3bd05b","modified":1636722490065,"created":1636455712318,"url":"https://dkanvas.herokuapp.com/api/courses/","name":"Cadastrar","description":"","method":"POST","body":{"mimeType":"application/json","text":"{\n    \"name\": \"Python\"\n}\n"},"parameters":[],"headers":[{"name":"Content-Type","value":"application/json","id":"pair_55d5ec68f48343d9ae3bdd6ad9b566a6"},{"id":"pair_fbc572429fca4fb08c03f7368ccc440f","name":"Authorization","value":"token 9ffe4b3a3d9e9ed4ba24573ec35be7e0fc3bd9e3","description":""}],"authentication":{},"metaSortKey":-1636455712318,"isPrivate":false,"settingStoreCookies":true,"settingSendCookies":true,"settingDisableRenderRequestBody":false,"settingEncodeUrl":true,"settingRebuildPath":true,"settingFollowRedirects":"global","_type":"request"},{"_id":"env_a057096c2d7f441b14fed3b763690526571dd511","parentId":"wrk_6b6bbda01c4f48afb01b2b6240a4e5eb","modified":1625581782042,"created":1625581782042,"name":"Base Environment","data":{},"dataPropertyOrder":null,"color":null,"isPrivate":false,"metaSortKey":1625581782042,"_type":"environment"},{"_id":"jar_a057096c2d7f441b14fed3b763690526571dd511","parentId":"wrk_6b6bbda01c4f48afb01b2b6240a4e5eb","modified":1625753261368,"created":1625753261368,"name":"Default Jar","cookies":[],"_type":"cookie_jar"},{"_id":"spc_ed6524f0170c4d3b8fabed6efd4267b0","parentId":"wrk_6b6bbda01c4f48afb01b2b6240a4e5eb","modified":1636328701881,"created":1625581781992,"fileName":"Kanvas","contents":"","contentType":"yaml","_type":"api_spec"},{"_id":"env_d4bcd2d0ff3445fe82d046de4d684843","parentId":"env_a057096c2d7f441b14fed3b763690526571dd511","modified":1625581810783,"created":1625581790030,"name":"DEVELOPMENT","data":{"base_url":"https://happy-budget-api.herokuapp.com/"},"dataPropertyOrder":{"&":["base_url"]},"color":null,"isPrivate":false,"metaSortKey":1625581790030,"_type":"environment"}]}